{
  "marcus": {
    "name": "Marcus Tan",
    "age": 32,
    "archetype": "loner",
    "color": "#60a5fa",
    "scores": {
      "trust": 22,
      "openness": 18,
      "ambition": 45,
      "loneliness": 77,
      "resilience": 83
    },
    "mood": "restless",
    "location": {
      "x": 80,
      "y": 26
    },
    "shelter": "tent",
    "relationships": {
      "ryan": {
        "closeness": 25,
        "tension": 15,
        "attraction": 0
      },
      "jade": {
        "closeness": 14,
        "tension": 10,
        "attraction": 11
      }
    },
    "bio": "32, ex-navy. Came here after a bad breakup he never talks about. Built his tent on the eastern cliff. Notices everything. Says nothing."
  },
  "ryan": {
    "name": "Ryan Lim",
    "age": 28,
    "archetype": "builder",
    "color": "#fbbf24",
    "scores": {
      "trust": 77,
      "openness": 87,
      "ambition": 70,
      "loneliness": 31,
      "resilience": 39
    },
    "mood": "hopeful",
    "location": {
      "x": 45,
      "y": 50
    },
    "shelter": "house",
    "relationships": {
      "marcus": {
        "closeness": 25,
        "tension": 10,
        "attraction": 0
      },
      "jade": {
        "closeness": 50,
        "tension": 5,
        "attraction": 24
      }
    },
    "bio": "28, ex-property agent. Built a proper house in his first week. Always makes room for people. Gets hurt easily but forgives even easier."
  },
  "jade": {
    "name": "Jade Ng",
    "age": 26,
    "archetype": "drifter",
    "color": "#f472b6",
    "scores": {
      "trust": 58,
      "openness": 74,
      "ambition": 40,
      "loneliness": 38,
      "resilience": 60
    },
    "mood": "alive",
    "location": {
      "x": 78,
      "y": 27
    },
    "shelter": "hammock",
    "relationships": {
      "marcus": {
        "closeness": 14,
        "tension": 10,
        "attraction": 3
      },
      "ryan": {
        "closeness": 50,
        "tension": 5,
        "attraction": 7
      }
    },
    "bio": "26, ex-startup marketing. Burned out, quit everything, ended up here. Sleeps wherever feels right. Both guys think she's thinking about them. She isn't."
  }
}